lindemann/__init__.py
lindemann/__main__.py
lindemann/index/__init__.py
lindemann/index/mem_use.py
lindemann/index/online_atoms.py
lindemann/index/online_frames.py
lindemann/index/online_trj.py
lindemann/index/parallel_trj.py
lindemann/index/per_atoms.py
lindemann/index/per_frames.py
lindemann/index/per_trj.py
lindemann/main.py
lindemann/py.typed
lindemann/trajectory/__init__.py
lindemann/trajectory/plt_plot.py
lindemann/trajectory/read.py
lindemann/trajectory/save.py
lindemann-0.10.0.dist-info/LICENSE
lindemann-0.10.0.dist-info/METADATA
lindemann-0.10.0.dist-info/WHEEL
lindemann-0.10.0.dist-info/entry_points.txt
lindemann-0.10.0.dist-info/RECORD
