Metadata-Version: 2.1
Name: lindemann
Version: 0.10.0
Summary: lindemann is a python package to calculate the Lindemann index  of a lammps trajectory as well as the progression of the Lindemann index per frame of temperature ramps  for phase transition analysis.
Home-page: https://github.com/N720720/lindemann
License: GPL-3.0-or-later
Keywords: Molecular Dynamics,Cheminformatics,Lindemann,Lindemann Index,Cheminformatics,Phase transition
Author: N720720
Author-email: s.thurm@protonmail.com
Requires-Python: >=3.9,<3.12
Classifier: Development Status :: 4 - Beta
Classifier: Intended Audience :: Science/Research
Classifier: License :: OSI Approved :: GNU General Public License v3 or later (GPLv3+)
Classifier: Operating System :: MacOS :: MacOS X
Classifier: Operating System :: Microsoft :: Windows
Classifier: Operating System :: POSIX :: Linux
Classifier: Programming Language :: Python :: 3
Classifier: Programming Language :: Python :: 3.9
Classifier: Programming Language :: Python :: 3.10
Classifier: Programming Language :: Python :: 3.11
Classifier: Topic :: Scientific/Engineering :: Bio-Informatics
Classifier: Topic :: Scientific/Engineering :: Chemistry
Classifier: Topic :: Scientific/Engineering :: Physics
Requires-Dist: importlib-metadata (>=7.1.0,<8.0.0)
Requires-Dist: intel-cmplr-lib-rt (>=2024.1.2,<2025.0.0) ; sys_platform == "linux"
Requires-Dist: intel-cmplr-lib-rt (>=2024.1.2,<2025.0.0) ; sys_platform == "win32"
Requires-Dist: matplotlib (>=3.9.0,<4.0.0)
Requires-Dist: numba (>=0.59.1,<0.60.0)
Requires-Dist: numpy (>=1.26.4,<2.0.0)
Requires-Dist: ovito (>=3.10.6,<4.0.0)
Requires-Dist: pathlib (>=1.0.1,<2.0.0)
Requires-Dist: psutil (>=5.9.8,<6.0.0)
Requires-Dist: rich (>=13.7.1,<14.0.0)
Requires-Dist: typer (>=0.12.3,<0.13.0)
Project-URL: Repository, https://github.com/N720720/lindemann
